azure_blob_run/VERSION
azure_blob_run/__init__.py
azure_blob_run-0.1.3.dist-info/METADATA
azure_blob_run-0.1.3.dist-info/WHEEL
azure_blob_run-0.1.3.dist-info/licenses/LICENSE
azure_blob_run-0.1.3.dist-info/RECORD
