Metadata-Version: 2.4
Name: azure-blob-run
Version: 0.1.3
Summary: Run Azure Blob Object
License: MIT
License-File: LICENSE
Author: Allen Chou
Author-email: f1470891079@gmail.com
Requires-Python: >=3.11,<4
Classifier: License :: OSI Approved :: MIT License
Classifier: Programming Language :: Python :: 3
Classifier: Programming Language :: Python :: 3.11
Classifier: Programming Language :: Python :: 3.12
Classifier: Programming Language :: Python :: 3.13
Classifier: Programming Language :: Python :: 3.14
Requires-Dist: azure-storage-blob
Requires-Dist: pydantic (>=2)
Requires-Dist: pydantic-settings
Requires-Dist: str-or-none
Requires-Dist: yarl
Project-URL: Homepage, https://github.com/allen2c/azure-blob-run
Project-URL: PyPI, https://pypi.org/project/azure-blob-run/
Project-URL: Repository, https://github.com/allen2c/azure-blob-run
